envio/__init__.py
envio/tests.py
envio-1.0.1.dist-info/METADATA
envio-1.0.1.dist-info/RECORD
envio-1.0.1.dist-info/WHEEL
envio-1.0.1.dist-info/top_level.txt
